rotaryselect.py
circuitpython_rotaryselect-1.0.1.dist-info/LICENSE
circuitpython_rotaryselect-1.0.1.dist-info/METADATA
circuitpython_rotaryselect-1.0.1.dist-info/WHEEL
circuitpython_rotaryselect-1.0.1.dist-info/top_level.txt
circuitpython_rotaryselect-1.0.1.dist-info/RECORD
