Metadata-Version: 2.1
Name: circuitpython-rotaryselect
Version: 1.0.1
Summary: A circular rotary selection widget
Author-email: foamyguy <foamyguy@gmail.com>
License: MIT
Project-URL: Homepage, https://github.com/foamyguy/CircuitPython_RotarySelect
Keywords: adafruit,blinka,circuitpython,micropython,rotaryselect,GUI,widget,displayio,select,rotary,dial,circle,menu,selector
Classifier: Intended Audience :: Developers
Classifier: Topic :: Software Development :: Libraries
Classifier: Topic :: Software Development :: Embedded Systems
Classifier: Topic :: System :: Hardware
Classifier: License :: OSI Approved :: MIT License
Classifier: Programming Language :: Python :: 3
License-File: LICENSE
Requires-Dist: Adafruit-Blinka
Requires-Dist: adafruit-circuitpython-displayio-layout
Requires-Dist: adafruit-circuitpython-display-text
Requires-Dist: adafruit-circuitpython-display-shapes
Requires-Dist: adafruit-circuitpython-imageload
Provides-Extra: optional
